ganttify
