Metadata-Version: 2.1
Name: ganttify
Version: 0.2.0
Summary: Turn test results into a Gantt chart
Home-page: UNKNOWN
Author: Matt Chun-Lum
License: UNKNOWN
Keywords: ganttify
Platform: UNKNOWN
